biomedsheets/__init__.py
biomedsheets/__main__.py
biomedsheets/_version.py
biomedsheets/io.py
biomedsheets/models.py
biomedsheets/naming.py
biomedsheets/ref_resolver.py
biomedsheets/requests_resource.py
biomedsheets/union_find.py
biomedsheets/validation.py
biomedsheets/data/sheet.schema.json
biomedsheets/data/std_fields.json
biomedsheets/io_tsv/__init__.py
biomedsheets/io_tsv/base.py
biomedsheets/io_tsv/cancer.py
biomedsheets/io_tsv/generic.py
biomedsheets/io_tsv/germline.py
biomedsheets/shortcuts/__init__.py
biomedsheets/shortcuts/base.py
biomedsheets/shortcuts/cancer.py
biomedsheets/shortcuts/generic.py
biomedsheets/shortcuts/germline.py
biomedsheets-0.4.dist-info/DESCRIPTION.rst
biomedsheets-0.4.dist-info/METADATA
biomedsheets-0.4.dist-info/RECORD
biomedsheets-0.4.dist-info/WHEEL
biomedsheets-0.4.dist-info/entry_points.txt
biomedsheets-0.4.dist-info/metadata.json
biomedsheets-0.4.dist-info/top_level.txt
tests/__init__.py
tests/test_io_tsv_cancer.py
tests/test_io_tsv_cancer_custom_fields.py
tests/test_io_tsv_generic.py
tests/test_io_tsv_generic_custom_fields.py
tests/test_io_tsv_germline.py
tests/test_main.py
tests/test_ref_resolver.py
tests/test_shortcuts_cancer.py
tests/test_shortcuts_germline.py
tests/data/base.json
tests/data/example_cancer.json
tests/data/example_cancer_matched.tsv
tests/data/example_germline_variants.tsv
tests/data/included1.json
tests/data/included2.json
tests/data/included3.json
