Metadata-Version: 2.0
Name: biomedsheets
Version: 0.4
Summary: Python 3 library for accessing and managing BioMedical sheets
Home-page: https://github.com/bihealth/biomedsheets
Author: Manuel Holtgrewe
Author-email: manuel.holtgrewe@bihealth.de
License: MIT license
Keywords: biomedsheets
Platform: UNKNOWN
Classifier: Development Status :: 2 - Pre-Alpha
Classifier: Intended Audience :: Developers
Classifier: License :: OSI Approved :: MIT License
Classifier: Natural Language :: English
Classifier: Programming Language :: Python :: 3
Classifier: Programming Language :: Python :: 3.3
Classifier: Programming Language :: Python :: 3.4
Classifier: Programming Language :: Python :: 3.5
Requires-Dist: codacy-coverage (==1.3.6)
Requires-Dist: coverage (==4.3.4)
Requires-Dist: decorator (==4.0.11)
Requires-Dist: flake8 (==3.2.1)
Requires-Dist: jsonpath-rw (==1.4.0)
Requires-Dist: jsonschema (==2.5.1)
Requires-Dist: ply (==3.10)
Requires-Dist: pytest (==3.0.6)
Requires-Dist: pytest-cov (==2.4.0)
Requires-Dist: pytest-flake8 (==0.8.1)
Requires-Dist: requests (>=2.12.4)
Requires-Dist: requests-file (>=1.4.1)
Requires-Dist: ruamel.yaml (>=0.15.18)
Requires-Dist: six (==1.10.0)
Requires-Dist: typing (==3.5.3.0)
